evo_featureflags_protobuf-0.3.0.dist-info/METADATA
evo_featureflags_protobuf-0.3.0.dist-info/WHEEL
featureflags_protobuf/__init__.py
featureflags_protobuf/backend.proto
featureflags_protobuf/backend_pb2.py
featureflags_protobuf/graph.proto
featureflags_protobuf/graph_pb2.py
featureflags_protobuf/service.proto
featureflags_protobuf/service_grpc.py
featureflags_protobuf/service_pb2.py
featureflags_protobuf/service_pb2_grpc.py
evo_featureflags_protobuf-0.3.0.dist-info/RECORD
