Metadata-Version: 2.1
Name: evo-featureflags-protobuf
Version: 0.3.0
Summary: Protocol Buffers stub files for feature flags service
Author-Email: d.zakharchuk <d.zakharchuk@smartweb.com.ua>, m.kindritskiy <m.kindritskiy@smartweb.com.ua>, Vladimir Magamedov <vladimir@magamedov.com>
License: MIT
Requires-Python: >=3.7
Provides-Extra: protoc
Requires-Dist: grpcio-tools>=1.59.0; extra == "protoc"
Requires-Dist: hiku==0.7.1; extra == "protoc"
Requires-Dist: protobuf>=4.24.4; extra == "protoc"
Requires-Dist: grpclib>=0.4.6; extra == "protoc"
